{
	"configurations" : 
	[
		{
			"directories" : 
			[
				{
					"build" : ".",
					"childIndexes" : 
					[
						1
					],
					"jsonFile" : "directory-.-Debug-d0094a50bb2071803777.json",
					"minimumCMakeVersion" : 
					{
						"string" : "3.28"
					},
					"projectIndex" : 0,
					"source" : "."
				},
				{
					"build" : "MMQLC",
					"jsonFile" : "directory-MMQLC-Debug-dd883f46ca5f03e4e238.json",
					"minimumCMakeVersion" : 
					{
						"string" : "3.28"
					},
					"parentIndex" : 0,
					"projectIndex" : 0,
					"source" : "mmqlc-source-code",
					"targetIndexes" : 
					[
						0
					]
				}
			],
			"name" : "Debug",
			"projects" : 
			[
				{
					"directoryIndexes" : 
					[
						0,
						1
					],
					"name" : "mmql-package",
					"targetIndexes" : 
					[
						0
					]
				}
			],
			"targets" : 
			[
				{
					"directoryIndex" : 1,
					"id" : "MmQLC::@1372cffa5b13cacb8806",
					"jsonFile" : "target-MmQLC-Debug-2b1a1a0dfa5550728e1c.json",
					"name" : "MmQLC",
					"projectIndex" : 0
				}
			]
		}
	],
	"kind" : "codemodel",
	"paths" : 
	{
		"build" : "C:/Users/EngineersPC/Documents/GitHub/mmql-package/cmake-build-debug",
		"source" : "C:/Users/EngineersPC/Documents/GitHub/mmql-package"
	},
	"version" : 
	{
		"major" : 2,
		"minor" : 6
	}
}
